arango_cve_processor/__init__.py
arango_cve_processor/__main__.py
arango_cve_processor/config.py
arango_cve_processor/managers/__init__.py
arango_cve_processor/managers/base_manager.py
arango_cve_processor/managers/cpe_match.py
arango_cve_processor/managers/cve_attack.py
arango_cve_processor/managers/cve_capec.py
arango_cve_processor/managers/cve_cwe.py
arango_cve_processor/managers/cve_kev.py
arango_cve_processor/managers/cve_kev_vulncheck.py
arango_cve_processor/tools/__init__.py
arango_cve_processor/tools/cpe.py
arango_cve_processor/tools/cpe_db.py
arango_cve_processor/tools/nvd.py
arango_cve_processor/tools/retriever.py
arango_cve_processor/tools/utils.py
arango_cve_processor-1.4.9.dist-info/METADATA
arango_cve_processor-1.4.9.dist-info/WHEEL
arango_cve_processor-1.4.9.dist-info/entry_points.txt
arango_cve_processor-1.4.9.dist-info/licenses/LICENSE
arango_cve_processor-1.4.9.dist-info/RECORD
