Metadata-Version: 2.4
Name: arango_cve_processor
Version: 1.4.9
Summary: A small python script that enriches Vulnerability STIX Objects with other intel
Project-URL: Homepage, https://github.com/muchdogesec/arango_cve_processor
Project-URL: Issues, https://github.com/muchdogesec/arango_cve_processor/issues
Project-URL: dogesec HQ, https://dogesec.com
Author: dogesec
Maintainer: dogesec
License-File: LICENSE
Classifier: License :: OSI Approved :: Apache Software License
Classifier: Operating System :: OS Independent
Classifier: Programming Language :: Python :: 3
Requires-Python: >=3.9
Requires-Dist: arango-cve-processor
Requires-Dist: jsonschema>=4.22.0; python_version >= '3.8'
Requires-Dist: python-arango>=7.9.1; python_version >= '3.8'
Requires-Dist: requests>=2.32.4; python_version >= '3.7'
Requires-Dist: stix2
Requires-Dist: stix2arango
Requires-Dist: stix2extensions>=2.0.1
Requires-Dist: tqdm>=4.66.4; python_version >= '3.7'
